LICENSE
MANIFEST.in
README.md
README.rst
setup.cfg
setup.py
test-travis.sh
test.sh
monero_serialize/__init__.py
monero_serialize/helpers.py
monero_serialize/protobuf.py
monero_serialize/xmrboost.py
monero_serialize/xmrjson.py
monero_serialize/xmrobj.py
monero_serialize/xmrrpc.py
monero_serialize/xmrserialize.py
monero_serialize/xmrtypes.py
monero_serialize.egg-info/PKG-INFO
monero_serialize.egg-info/SOURCES.txt
monero_serialize.egg-info/dependency_links.txt
monero_serialize.egg-info/requires.txt
monero_serialize.egg-info/top_level.txt
monero_serialize/core/__init__.py
monero_serialize/core/base_types.py
monero_serialize/core/erefs.py
monero_serialize/core/int_serialize.py
monero_serialize/core/message_types.py
monero_serialize/core/obj_helper.py
monero_serialize/core/readwriter.py
monero_serialize/core/versioning.py
monero_serialize/messages/__init__.py
monero_serialize/messages/addr.py
monero_serialize/messages/base.py
monero_serialize/messages/ct_keys.py
monero_serialize/messages/tx_construct.py
monero_serialize/messages/tx_dest_entry.py
monero_serialize/messages/tx_ecdh.py
monero_serialize/messages/tx_extra.py
monero_serialize/messages/tx_full.py
monero_serialize/messages/tx_prefix.py
monero_serialize/messages/tx_rsig.py
monero_serialize/messages/tx_rsig_boro.py
monero_serialize/messages/tx_rsig_bulletproof.py
monero_serialize/messages/tx_sig.py
monero_serialize/messages/tx_src_entry.py
monero_serialize/tests/__init__.py
monero_serialize/tests/test_base.py
monero_serialize/tests/test_data.py
monero_serialize/tests/test_xmr_base.py
monero_serialize/tests/test_xmr_boost.py
monero_serialize/tests/test_xmr_json.py
monero_serialize/tests/test_xmr_rpc.py
monero_serialize/tests/data/tx_01.txt
monero_serialize/tests/data/tx_hf13.txt
monero_serialize/tests/data/tx_hf15.txt
monero_serialize/tests/data/tx_metadata_01.txt
monero_serialize/tests/data/tx_prefix_01.txt
monero_serialize/tests/data/tx_unsigned_01.txt
monero_serialize/tests/data/tx_unsigned_01_bc.txt
monero_serialize/tests/data/tx_unsigned_02.txt