Metadata-Version: 2.1
Name: monero-serialize
Version: 3.0.5
Summary: Monero serialization
Home-page: https://github.com/ph4r05/monero-serialize
Author: Dusan Klinec
Author-email: dusan.klinec@gmail.com
License: MIT
Platform: UNKNOWN
Classifier: Development Status :: 3 - Alpha
Classifier: Intended Audience :: Developers
Classifier: Programming Language :: Python
Classifier: Programming Language :: Python :: 3.5
Classifier: Programming Language :: Python :: 3.6
Classifier: Topic :: Security
Requires-Python: >=3.5
Provides-Extra: dev
Provides-Extra: docs
